lcdoc/__init__.py
lcdoc/const.py
lcdoc/log.py
lcdoc/lp.py
lcdoc/lp_session.py
lcdoc/lprunner.py
lcdoc/tools.py
lcdoc/assets/mkdocs/mkdocs.yml
lcdoc/assets/mkdocs/lcd/partials/footer.html
lcdoc/assets/mkdocs/lcd/src/_snippets/abbr.txt
lcdoc/assets/mkdocs/lcd/src/_snippets/critic-accept-example.txt
lcdoc/assets/mkdocs/lcd/src/_snippets/critic-preview-example.txt
lcdoc/assets/mkdocs/lcd/src/_snippets/links.txt
lcdoc/assets/mkdocs/lcd/src/_snippets/mathjax.txt
lcdoc/assets/mkdocs/lcd/src/_snippets/refs.txt
lcdoc/assets/mkdocs/lcd/src/md/keepachangelog/README.txt.tmpl
lcdoc/assets/mkdocs/lcd/src/md/keepachangelog/changelog.md.tmpl
lcdoc/assets/mkdocs/lcd/src/md/keepachangelog/commit.md.tmpl
lcdoc/assets/mkdocs/lcd/src/md/keepachangelog/section.md.tmpl
lcdoc/assets/mkdocs/lcd/src/md/keepachangelog/version.md.tmpl
lcdoc/call_flows/auto_docs.py
lcdoc/call_flows/call_flow_charting.py
lcdoc/call_flows/call_flow_logging.py
lcdoc/call_flows/markdown.py
lcdoc/call_flows/viz_sequence.py
lcdoc/mkdocs/markdown.py
lcdoc/mkdocs/tools.py
lcdoc/mkdocs/blacklist/__init__.py
lcdoc/mkdocs/custom_dir/__init__.py
lcdoc/mkdocs/find_pages/__init__.py
lcdoc/mkdocs/find_pages/autodocs.py
lcdoc/mkdocs/lp/__init__.py
lcdoc/mkdocs/lp/assets/logo_devapps.svg
lcdoc/mkdocs/lp/assets/arch/ax_termcasts.js
lcdoc/mkdocs/lp/assets/css/xterm.min.css
lcdoc/mkdocs/lp/assets/javascript/Rx.min.js
lcdoc/mkdocs/lp/assets/javascript/fa_all.js
lcdoc/mkdocs/lp/assets/javascript/lc.js
lcdoc/mkdocs/lp/assets/javascript/tables.js
lcdoc/mkdocs/lp/assets/javascript/tablesort.min.js
lcdoc/mkdocs/lp/assets/javascript/xterm-addon-fit.min.js
lcdoc/mkdocs/lp/assets/javascript/xterm-addon-search.min.js
lcdoc/mkdocs/lp/assets/javascript/xterm.4.9.0.min.js
lcdoc/mkdocs/lp/assets/plantuml/all_dark.puml
lcdoc/mkdocs/lp/assets/plantuml/dark_blue.puml
lcdoc/mkdocs/lp/plugs/about/credits.md
lcdoc/mkdocs/lp/plugs/bash/__init__.py
lcdoc/mkdocs/lp/plugs/chart/__init__.py
lcdoc/mkdocs/lp/plugs/chart/docs/index.md
docutools-2025.11.8.dist-info/METADATA
docutools-2025.11.8.dist-info/WHEEL
docutools-2025.11.8.dist-info/entry_points.txt
docutools-2025.11.8.dist-info/licenses/LICENSE
docutools-2025.11.8.dist-info/RECORD
