Metadata-Version: 2.4
Name: docutools
Version: 2025.11.8
Summary: Documentation Tools for the Mkdocs Material Framework
Project-URL: Repository, https://github.com/axiros/docutools
Project-URL: Homepage, https://axiros.github.io/docutools/
Author-email: Gunther Klessinger <gkle_ss_ing_er@gmx.de>
License-Expression: BSD-2-Clause
License-File: LICENSE
Classifier: Development Status :: 4 - Beta
Classifier: License :: OSI Approved :: BSD License
Classifier: Programming Language :: Python :: 3
Classifier: Programming Language :: Python :: 3.9
Classifier: Programming Language :: Python :: 3.10
Classifier: Programming Language :: Python :: 3.11
Classifier: Programming Language :: Python :: 3.12
Requires-Python: >=3.9
Requires-Dist: anybadge>=1.7.0
Requires-Dist: coverage>=6.0.2
Requires-Dist: diagrams
Requires-Dist: git-changelog
Requires-Dist: httpx>=0.17.1
Requires-Dist: imagesize>=1.0.0
Requires-Dist: inflection>=0.5.1
Requires-Dist: markdown-include>=0.8.1
Requires-Dist: markupsafe==2.0.1
Requires-Dist: mkdocs-exclude>=1.0.2
Requires-Dist: mkdocs-macros-plugin>=0.5.12
Requires-Dist: mkdocs-material>=8.0.0
Requires-Dist: mkdocs-pymdownx-material-extras>=1.1.3
Requires-Dist: mkdocs>=1.1.2
Requires-Dist: pycond>=2.0.0
Requires-Dist: pytest-cov>=2.10.1
Requires-Dist: pytest-randomly>=3.4.1
Requires-Dist: pytest-sugar>=0.9.4
Requires-Dist: pytest-xdist>=2.1.0
Requires-Dist: pytest>=6.0.1
Requires-Dist: toml>=0.10.1
Provides-Extra: dev
Requires-Dist: matplotlib>=3.0.0; extra == 'dev'
Requires-Dist: mypy>=0.900; extra == 'dev'
Requires-Dist: numpy>=1.0.0; extra == 'dev'
Requires-Dist: ruff>=0.1.0; extra == 'dev'
